apiautomationtools/__init__.py
apiautomationtools/batch_generation/__init__.py
apiautomationtools/batch_generation/batch_generation.py
apiautomationtools/client/__init__.py
apiautomationtools/client/async_requests.py
apiautomationtools/client/httpx_requests.py
apiautomationtools/helpers/__init__.py
apiautomationtools/helpers/dictionary_helpers.py
apiautomationtools/helpers/directory_helpers.py
apiautomationtools/helpers/json_helpers.py
apiautomationtools/logging/__init__.py
apiautomationtools/logging/logger.py
apiautomationtools/pytest/__init__.py
apiautomationtools/pytest/api_pytest.py
apiautomationtools/reporting/__init__.py
apiautomationtools/reporting/response_csv.py
apiautomationtools/validations/__init__.py
apiautomationtools/validations/validations.py
examples/__init__.py
examples/api_base_pytest_example.py
examples/test_get_example.py
scripts/__init__.py
tests/__init__.py
tests/batch_generation/__init__.py
tests/batch_generation/test_batch_generation.py
tests/batch_generation/test_generate_bad_bodies.py
tests/batch_generation/test_generate_bad_urls.py
tests/batch_generation/test_generate_unsafe_bodies.py
tests/client/__init__.py
tests/client/aiohttp/__init__.py
tests/client/aiohttp/test_async_requests.py
tests/client/aiohttp/test_async_requests_event_loop.py
tests/client/aiohttp/test_dict_as_form_data.py
tests/client/httpx/__init__.py
tests/client/httpx/test_form_data_separation.py
tests/client/httpx/test_httpx_requests.py
tests/client/httpx/test_httpx_requests_reuse.py
tests/helpers/__init__.py
tests/helpers/dictionary_helpers/__init__.py
tests/helpers/dictionary_helpers/test_compare_dictionaries.py
tests/helpers/dictionary_helpers/test_flatten_unflatten.py
tests/helpers/directory_helpers/__init__.py
tests/helpers/directory_helpers/test_directory_helpers.py
tests/helpers/json_helpers/__init__.py
tests/helpers/json_helpers/test_json_helpers.py
tests/logging/__init__.py
tests/logging/test_logger.py
tests/pytest/__init__.py
tests/pytest/api_pytest/__init__.py
api_automation_tools-2.0.0.dist-info/LICENSE.txt
api_automation_tools-2.0.0.dist-info/METADATA
api_automation_tools-2.0.0.dist-info/WHEEL
api_automation_tools-2.0.0.dist-info/top_level.txt
api_automation_tools-2.0.0.dist-info/RECORD
