Metadata-Version: 2.1
Name: api-automation-tools
Version: 2.0.0
Summary: Tools for API automation
Home-page: https://github.com/rakutentech/api-automation-tools
Author: Ashton Szabo
Author-email: ashton.szabo@rakuten.com
Classifier: Programming Language :: Python :: 3
Classifier: License :: OSI Approved :: MIT License
Classifier: Operating System :: OS Independent
Requires-Python: >=3.10
License-File: LICENSE.txt
Requires-Dist: pytest
Requires-Dist: pytest-xdist
Requires-Dist: aiohttp
Requires-Dist: pypeln
Requires-Dist: numpy
Requires-Dist: orjson
Requires-Dist: httpx
Requires-Dist: pytest-asyncio
